odoo/addons/event_registration_lang/README.rst
odoo/addons/event_registration_lang/__init__.py
odoo/addons/event_registration_lang/__manifest__.py
odoo/addons/event_registration_lang/hooks.py
odoo/addons/event_registration_lang/i18n/event_registration_lang.pot
odoo/addons/event_registration_lang/i18n/it.po
odoo/addons/event_registration_lang/models/__init__.py
odoo/addons/event_registration_lang/models/event_registration.py
odoo/addons/event_registration_lang/readme/CONTRIBUTORS.rst
odoo/addons/event_registration_lang/readme/DESCRIPTION.rst
odoo/addons/event_registration_lang/static/description/icon.png
odoo/addons/event_registration_lang/static/description/index.html
odoo/addons/event_registration_lang/tests/__init__.py
odoo/addons/event_registration_lang/tests/test_event_registration_lang.py
odoo/addons/event_registration_lang/views/event_registration.xml
odoo13_addon_event_registration_lang-13.0.1.0.1.dev6.dist-info/METADATA
odoo13_addon_event_registration_lang-13.0.1.0.1.dev6.dist-info/WHEEL
odoo13_addon_event_registration_lang-13.0.1.0.1.dev6.dist-info/top_level.txt
odoo13_addon_event_registration_lang-13.0.1.0.1.dev6.dist-info/RECORD
